volikos/ast_nodes.py
volikos/cli.py
volikos/codegen.py
volikos/lexer.py
volikos/parser.py
volikos-0.2.1.dist-info/METADATA
volikos-0.2.1.dist-info/WHEEL
volikos-0.2.1.dist-info/entry_points.txt
volikos-0.2.1.dist-info/top_level.txt
volikos-0.2.1.dist-info/RECORD
