Metadata-Version: 2.4
Name: volikos
Version: 0.2.1
Summary: A tiny, intro-friendly LLVM language.
Author-email: codesft <hello@codesft.dev>
Requires-Python: >=3.8
Requires-Dist: llvmlite
Requires-Dist: rply
Requires-Dist: click
